{
    "id канала": "UCwHL6WHUarjGfUM_586me8w",
    "название канала": "HighLoad Channel",
    "описание канала": "HighLoad++ — крупнейшая в России профессиональная IT-конференция. Более 200 докладов по тематике высоких нагрузок, более 3000 участников. Программа охватывает такие аспекты веб-разработки, как архитектура крупных проектов, базы данных и системы хранения, системное администрирование, нагрузочное тестирование, эксплуатация крупных проектов и другие направления, связанные с высоконагруженными системами.\n\nНа нашем канале мы публикуем видео докладов с HighLoad+, РИТ+ и других конференций. Самые свежие записи доступны, как обычно, участникам самих конференций и тем, кто купил эти записи. \n\nПриглашаем на Saint HighLoad 2023, которая пройдет 26 и 27 июня 2023 в Санкт-Петербурге!\nПрограмма, подробности и билеты по ссылке: http://bit.ly/3JZHEg2\n\nКалендарь всех конференций Онтико — на http://ontico.ru/",
    "ссылка на канал": "https://www.youtube.com/@highloadchannel",
    "количество подписчиков": "74700",
    "количество видео": "2127",
    "общее количество просмотров": "7443828"
}